genox.py
genox-0.2.3.dist-info/METADATA
genox-0.2.3.dist-info/WHEEL
genox-0.2.3.dist-info/entry_points.txt
genox-0.2.3.dist-info/top_level.txt
genox-0.2.3.dist-info/RECORD
