Metadata-Version: 2.1
Name: genox
Version: 0.2.3
Summary: genox - extremely simple static site generator
Home-page: https://github.com/oxalorg/genox
Author: oxalorg
Author-email: mitesh@oxal.org
License: MIT
Platform: UNKNOWN
Requires-Python: >=3.6
Requires-Dist: markdown2
Requires-Dist: pyyaml
Requires-Dist: jinja2
Requires-Dist: pygments
